README.rst
setup.cfg
setup.py
aggravator/__init__.py
aggravator.egg-info/PKG-INFO
aggravator.egg-info/SOURCES.txt
aggravator.egg-info/dependency_links.txt
aggravator.egg-info/entry_points.txt
aggravator.egg-info/requires.txt
aggravator.egg-info/top_level.txt