Metadata-Version: 1.0
Name: aggravator
Version: 0.4.0
Summary: Ansible inventory script to aggregate other inventory sources
Home-page: https://github.com/petercb/aggravator
Author: Peter Burns
Author-email: pcburns@outlook.com
License: MIT
Keywords: ansible
Platform: UNKNOWN
